tuna/__init__.py
tuna/main.py
tuna/version.py
tuna/cli/__init__.py
tuna/cli/main.py
tuna/cli/cmd/__init__.py
tuna/cli/cmd/clone.py
tuna/cli/cmd/init.py
tuna/cli/cmd/open_repo.py
tuna/cli/cmd/purge.py
tuna/cli/cmd/refresh.py
tuna/cli/cmd/serve.py
tuna/cli/cmd/train.py
tuna/cli/core/__init__.py
tuna/cli/core/authenticator.py
tuna/cli/core/constants.py
tuna/cli/core/docs.py
tuna/cli/core/learn.py
tuna/cli/core/scripts.py
tuna/cli/core/watchfiles.py
tuna/services/__init__.py
tuna/services/evaluator.py
tuna/services/github.py
tuna/services/jupyter.py
tuna/services/clouds/__init__.py
tuna/services/clouds/fluidstack.py
tuna/util/__init__.py
tuna/util/general.py
tuna/util/nbutil.py
tuna_cli-0.2.0.dist-info/LICENSE.md
tuna_cli-0.2.0.dist-info/METADATA
tuna_cli-0.2.0.dist-info/WHEEL
tuna_cli-0.2.0.dist-info/entry_points.txt
tuna_cli-0.2.0.dist-info/top_level.txt
tuna_cli-0.2.0.dist-info/RECORD
