Metadata-Version: 2.1
Name: tuna-cli
Version: 0.2.0
Summary: Fine tuning, reimagined. Welcome to tuna - we're simplifying cloud compute architecture, datasets, and more, to get your specialized AI from 0 to 1 ASAP.
Home-page: https://github.com/abhi-arya1/tuna
Author: Abhigyan Arya (Opennote Labs)
Author-email: "Abhigyan Arya (Opennote Labs)" <support@opennote.me>
Project-URL: Homepage, https://github.com/abhi-arya1/tuna
Project-URL: Issues, https://github.com/abhi-arya1/tuna/issues
Classifier: Programming Language :: Python :: 3
Classifier: License :: OSI Approved :: MIT License
Classifier: Operating System :: OS Independent
Requires-Python: >=3.12
License-File: LICENSE.md
Requires-Dist: inquirer
Requires-Dist: transformers
Requires-Dist: requests
Requires-Dist: halo
Requires-Dist: jupyterlab
Requires-Dist: nbformat
Requires-Dist: scikit-learn
Requires-Dist: tabulate
Requires-Dist: paramiko
Requires-Dist: watchdog
Requires-Dist: gputil
